risclog.cryptography-1.1-py3.9-nspkg.pth
risclog/cryptography/__init__.py
risclog/cryptography/fernet.py
risclog/cryptography/tests/__init__.py
risclog/cryptography/tests/test_fernet.py
risclog.cryptography-1.1.dist-info/AUTHORS.rst
risclog.cryptography-1.1.dist-info/LICENSE
risclog.cryptography-1.1.dist-info/METADATA
risclog.cryptography-1.1.dist-info/WHEEL
risclog.cryptography-1.1.dist-info/namespace_packages.txt
risclog.cryptography-1.1.dist-info/top_level.txt
risclog.cryptography-1.1.dist-info/RECORD
