Metadata-Version: 2.1
Name: risclog.cryptography
Version: 1.1
Summary: The CryptographyManager is a tool designed to securely encrypt and decrypt messages and data. It uses modern encryption techniques to protect confidential information.
Home-page: https://github.com/risclog-solution/risclog.cryptography
Author: riscLOG Solution GmbH
Author-email: info@risclog.de
License: MIT license
Keywords: risclog.cryptography
Classifier: Development Status :: 2 - Pre-Alpha
Classifier: Intended Audience :: Developers
Classifier: License :: OSI Approved :: MIT License
Classifier: Natural Language :: German
Classifier: Programming Language :: Python :: 3
Classifier: Programming Language :: Python :: 3.10
Classifier: Programming Language :: Python :: 3.11
Requires-Python: >=3.6
License-File: LICENSE
License-File: AUTHORS.rst
Requires-Dist: risclog.logging
Requires-Dist: cryptography
Provides-Extra: docs
Requires-Dist: Sphinx ; extra == 'docs'
Provides-Extra: test
Requires-Dist: pytest-cache ; extra == 'test'
Requires-Dist: pytest-cov ; extra == 'test'
Requires-Dist: pytest-flake8 ; extra == 'test'
Requires-Dist: pytest-rerunfailures ; extra == 'test'
Requires-Dist: pytest-sugar ; extra == 'test'
Requires-Dist: pytest-asyncio ; extra == 'test'
Requires-Dist: pytest ; extra == 'test'
Requires-Dist: coverage ; extra == 'test'
Requires-Dist: flake8 <4 ; extra == 'test'
